DockS/__init__.py
docks_stt-0.1.dist-info/METADATA
docks_stt-0.1.dist-info/WHEEL
docks_stt-0.1.dist-info/top_level.txt
docks_stt-0.1.dist-info/RECORD
