Metadata-Version: 2.4
Name: DockS-STT
Version: 0.1
Summary: This is a speech to text package created
Author: Satyam Singh
Author-email: satyam23153065@gmail.com
Dynamic: author
Dynamic: author-email
Dynamic: summary
